graphene_mongo/__init__.py
graphene_mongo/advanced_types.py
graphene_mongo/converter.py
graphene_mongo/fields.py
graphene_mongo/fields_async.py
graphene_mongo/registry.py
graphene_mongo/tests/__init__.py
graphene_mongo/tests/conftest.py
graphene_mongo/tests/fixtures/image.jpg
graphene_mongo/tests/models.py
graphene_mongo/tests/nodes.py
graphene_mongo/tests/nodes_async.py
graphene_mongo/tests/test_converter.py
graphene_mongo/tests/test_fields.py
graphene_mongo/tests/test_inputs.py
graphene_mongo/tests/test_mutation.py
graphene_mongo/tests/test_query.py
graphene_mongo/tests/test_relay_query.py
graphene_mongo/tests/test_relay_query_async.py
graphene_mongo/tests/test_types.py
graphene_mongo/tests/test_utils.py
graphene_mongo/tests/types.py
graphene_mongo/tests/utils.py
graphene_mongo/types.py
graphene_mongo/types_async.py
graphene_mongo/utils.py
graphene_mongo-0.4.4.dist-info/LICENSE
graphene_mongo-0.4.4.dist-info/METADATA
graphene_mongo-0.4.4.dist-info/WHEEL
graphene_mongo-0.4.4.dist-info/RECORD
