Metadata-Version: 2.1
Name: graphene-mongo
Version: 0.4.4
Summary: Graphene Mongoengine integration
Home-page: https://github.com/graphql-python/graphene-mongo
License: MIT
Keywords: graphene-mongo,graphql,api,graphql,protocol,relay,graphene,mongo,mongoengine
Author: Abaw Chen
Author-email: abaw.chen@gmail.com
Requires-Python: >=3.9,<4
Classifier: Development Status :: 4 - Beta
Classifier: Intended Audience :: Developers
Classifier: License :: OSI Approved :: MIT License
Classifier: Programming Language :: Python :: 3
Classifier: Programming Language :: Python :: 3.9
Classifier: Programming Language :: Python :: 3.10
Classifier: Programming Language :: Python :: 3.11
Classifier: Programming Language :: Python :: 3.12
Classifier: Programming Language :: Python :: Implementation :: PyPy
Classifier: Topic :: Software Development :: Libraries
Requires-Dist: asgiref (>=3.7.2,<4.0.0)
Requires-Dist: graphene (>=3.1.1)
Requires-Dist: graphene-federation (>=3.1.5)
Requires-Dist: mongoengine (>=0.27)
Requires-Dist: promise (>=2.3)
Project-URL: Repository, https://github.com/graphql-python/graphene-mongo
